restic/__init__.py
restic/errors.py
restic/restic_test.py
restic/internal/__init__.py
restic/internal/backup.py
restic/internal/backup_test.py
restic/internal/cat.py
restic/internal/cat_test.py
restic/internal/check.py
restic/internal/check_test.py
restic/internal/command_executor.py
restic/internal/copy.py
restic/internal/copy_test.py
restic/internal/find.py
restic/internal/find_test.py
restic/internal/forget.py
restic/internal/forget_test.py
restic/internal/generate.py
restic/internal/generate_test.py
restic/internal/init.py
restic/internal/init_test.py
restic/internal/key.py
restic/internal/key_test.py
restic/internal/list.py
restic/internal/list_test.py
restic/internal/restore.py
restic/internal/restore_test.py
restic/internal/rewrite.py
restic/internal/rewrite_test.py
restic/internal/self_update.py
restic/internal/self_update_test.py
restic/internal/snapshots.py
restic/internal/snapshots_test.py
restic/internal/stats.py
restic/internal/stats_test.py
restic/internal/unlock.py
restic/internal/unlock_test.py
restic/internal/version.py
restic/internal/version_test.py
resticpy-1.2.2.dist-info/LICENSE
resticpy-1.2.2.dist-info/METADATA
resticpy-1.2.2.dist-info/WHEEL
resticpy-1.2.2.dist-info/top_level.txt
resticpy-1.2.2.dist-info/RECORD
