Metadata-Version: 2.1
Name: resticpy
Version: 1.2.2
Summary: Restic backup Python wrapper
Home-page: https://github.com/mtlynch/resticpy.git
Author: Michael Lynch
Author-email: michael@mtlynch.io
License: MIT
Project-URL: repository, https://github.com/mtlynch/resticpy
Keywords: backup
Requires-Python: >=3.7
License-File: LICENSE
